{"metadata":{"usedHelpers":[],"marked":[],"modules":{"imports":[],"exports":{"exported":[],"specifiers":[]}}},"options":{"filename":"packages/zurb:foundation-sites/test/javascript/components/tabs.js","filenameRelative":"packages/zurb:foundation-sites/test/javascript/components/tabs.js","env":{"development":{"plugins":[]}},"retainLines":false,"highlightCode":true,"suppressDeprecationMessages":false,"presets":[],"plugins":[[[],{"generateLetDeclarations":true,"enforceStrictMode":false}],[[],null],[[],{"polyfill":false}],[[],null],[[],null],[[],null],[[],{"allowTopLevelThis":true,"strict":false,"loose":true}],[[],null],[[],null],[[],null],[[],null],[[],null],[[],null],[[],null],[[],null],[[],null],[[],null],[[],null],[[],null],[[],{"loose":true}],[[],{"loose":true}],[[],null],[[],{"loose":true}],[[],null],[[],null],[[],null],[[],null],[[],null],[[],null],[[],{"loose":true}],[[],null],[[],null],[[],null],[[],null],[[],null],[[],null],[[],null]],"ignore":[],"code":true,"metadata":true,"ast":true,"comments":true,"compact":false,"minified":false,"sourceMap":true,"sourceMaps":true,"sourceMapTarget":"packages/zurb:foundation-sites/test/javascript/components/tabs.js.map","sourceFileName":"packages/zurb:foundation-sites/test/javascript/components/tabs.js","babelrc":false,"sourceType":"module","moduleIds":false,"passPerPreset":false,"parserOpts":false,"generatorOpts":false,"basename":"tabs"},"ignored":false,"code":"describe('Tabs', function () {\n  var plugin;\n  var $html;\n  var template = \"\\n    <div>\\n      <ul class=\\\"tabs\\\" data-tabs id=\\\"example-tabs\\\">\\n        <li class=\\\"tabs-title is-active\\\"><a href=\\\"#panel1\\\" aria-selected=\\\"true\\\">Tab 1</a></li>\\n        <li class=\\\"tabs-title\\\"><a href=\\\"#panel2\\\">Tab 2</a></li>\\n        <li class=\\\"tabs-title\\\"><a data-tabs-target=\\\"panel3\\\" href=\\\"#/panel3\\\">Tab 3</a></li>\\n      </ul>\\n\\n      <div class=\\\"tabs-content\\\" data-tabs-content=\\\"example-tabs\\\">\\n        <div class=\\\"tabs-panel is-active\\\" id=\\\"panel1\\\">\\n          <p>one</p>\\n          <p>Check me out! I'm a super cool Tab panel with text content!</p>\\n        </div>\\n        <div class=\\\"tabs-panel\\\" id=\\\"panel2\\\">\\n          <p>two</p>\\n          <p>Check me out! I'm a super cool Tab panel with text content!</p>\\n        </div>\\n        <div class=\\\"tabs-panel\\\" id=\\\"panel3\\\">\\n          <p>three</p>\\n          <p>Check me out! I'm a super cool Tab panel with text content!</p>\\n        </div>\\n      </div>\\n    </div>\";\n  afterEach(function () {\n    plugin.destroy();\n    $html.remove();\n  });\n  describe('constructor()', function () {\n    it('stores the element and plugin options', function () {\n      $html = $(template).appendTo('body');\n      plugin = new Foundation.Tabs($html.find('[data-tabs]'), {});\n      plugin.$element.should.be.an('object');\n      plugin.options.should.be.an('object');\n    });\n  });\n  describe('init()', function () {\n    it('sets ARIA attributes', function () {\n      $html = $(template).appendTo('body');\n      plugin = new Foundation.Tabs($html.find('[data-tabs]'), {}); // Panels\n\n      $html.find('#panel1').should.have.attr('role', 'tabpanel');\n      $html.find('#panel1').should.have.attr('aria-labelledby', $html.find('[href=\"#panel1\"]').attr('id'));\n      $html.find('#panel1').should.not.have.attr('aria-hidden');\n      $html.find('#panel2').should.have.attr('aria-hidden', 'true'); // Links\n\n      $html.find('[href=\"#panel1\"]').should.have.attr('role', 'tab');\n      $html.find('[href=\"#panel1\"]').should.have.attr('aria-controls', $html.find('panel1').attr('id'));\n      $html.find('[href=\"#panel1\"]').should.have.attr('aria-selected', 'true');\n      $html.find('[href=\"#panel2\"]').should.have.attr('aria-selected', 'false'); // Tab list items\n\n      $html.find('[href=\"#panel1\"]').parent().should.have.attr('role', 'presentation');\n    });\n  });\n  describe('selectTab()', function () {\n    it('opens the selected tab via jQuery element', function () {\n      $html = $(template).appendTo('body');\n      plugin = new Foundation.Tabs($html.find('[data-tabs]'), {});\n      plugin.selectTab($html.find('#panel2'));\n      $html.find('#panel2').should.be.visible;\n    });\n    it('opens the selected tab via id string', function () {\n      $html = $(template).appendTo('body');\n      plugin = new Foundation.Tabs($html.find('[data-tabs]'), {});\n      plugin.selectTab('#panel2');\n      $html.find('#panel2').should.be.visible;\n    });\n    it('opens the selected tab with data-tabs-target attribute', function () {\n      $html = $(template).appendTo('body');\n      plugin = new Foundation.Tabs($html.find('[data-tabs]'), {});\n      plugin.selectTab('#/panel3');\n      $html.find('#panel3').should.be.visible;\n    });\n  });\n  describe('_handleTabChange()', function () {\n    it('opens the selected tab', function () {\n      $html = $(template).appendTo('body');\n      plugin = new Foundation.Tabs($html.find('[data-tabs]'), {});\n      plugin.selectTab('#panel2');\n      $html.find('#panel2').should.be.visible;\n      $html.find('#panel2').should.have.class('is-active');\n    });\n    it('sets ARIA attributes for open tab', function () {\n      $html = $(template).appendTo('body');\n      plugin = new Foundation.Tabs($html.find('[data-tabs]'), {});\n      plugin.selectTab('#panel2');\n      $html.find('#panel2').should.have.not.attr('aria-hidden');\n      $html.find('[href=\"#panel2\"]').should.have.attr('aria-selected', 'true');\n    });\n    it('hides the open tab', function () {\n      $html = $(template).appendTo('body');\n      plugin = new Foundation.Tabs($html.find('[data-tabs]'), {});\n      plugin.selectTab('#panel2');\n      $html.find('#panel1').should.be.hidden;\n      $html.find('#panel1').should.not.have.class('is-active');\n    });\n    it('sets ARIA attributes for closed tab', function () {\n      $html = $(template).appendTo('body');\n      plugin = new Foundation.Tabs($html.find('[data-tabs]'), {});\n      plugin.selectTab('#panel2');\n      $html.find('#panel1').should.be.have.attr('aria-hidden', 'true');\n      $html.find('[href=\"#panel1\"]').should.be.have.attr('aria-selected', 'false');\n    });\n    it('fires change.zf.tabs event with target as data', function (done) {\n      $html = $(template).appendTo('body');\n      plugin = new Foundation.Tabs($html.find('[data-tabs]'), {});\n      $html.one('change.zf.tabs', function (e, $target) {\n        e.stopPropagation();\n        $html.find('[href=\"#panel2\"]').parent()[0].should.be.equal($target[0]);\n        done();\n      });\n      plugin.selectTab('#panel2');\n    });\n  });\n  describe('keyboard events', function () {\n    it('switches to next tab on ARROW_RIGHT', function () {\n      $html = $(template).appendTo('body');\n      plugin = new Foundation.Tabs($html.find('[data-tabs]'), {});\n      $html.find('[href=\"#panel1\"]').focus().trigger(window.mockKeyboardEvent('ARROW_RIGHT'));\n      $html.find('#panel2').should.be.visible;\n      $html.find('#panel2').should.have.class('is-active');\n    });\n    it('switches to next tab on ARROW_DOWN', function () {\n      $html = $(template).appendTo('body');\n      plugin = new Foundation.Tabs($html.find('[data-tabs]'), {});\n      $html.find('[href=\"#panel1\"]').focus().trigger(window.mockKeyboardEvent('ARROW_DOWN'));\n      $html.find('#panel2').should.be.visible;\n      $html.find('#panel2').should.have.class('is-active');\n    });\n    it('switches to previous tab on ARROW_LEFT', function () {\n      $html = $(template).appendTo('body');\n      plugin = new Foundation.Tabs($html.find('[data-tabs]'), {});\n      $html.find('[href=\"#panel2\"]').focus().trigger(window.mockKeyboardEvent('ARROW_LEFT'));\n      $html.find('#panel1').should.be.visible;\n      $html.find('#panel1').should.have.class('is-active');\n    });\n    it('switches to previous tab on ARROW_UP', function () {\n      $html = $(template).appendTo('body');\n      plugin = new Foundation.Tabs($html.find('[data-tabs]'), {});\n      $html.find('[href=\"#panel2\"]').focus().trigger(window.mockKeyboardEvent('ARROW_UP'));\n      $html.find('#panel1').should.be.visible;\n      $html.find('#panel1').should.have.class('is-active');\n    });\n  });\n});","map":{"version":3,"sources":["packages/zurb:foundation-sites/test/javascript/components/tabs.js"],"names":["describe","plugin","$html","template","afterEach","destroy","remove","it","$","appendTo","Foundation","Tabs","find","$element","should","be","an","options","have","attr","not","parent","selectTab","visible","class","hidden","done","one","e","$target","stopPropagation","equal","focus","trigger","window","mockKeyboardEvent"],"mappings":"AAAAA,SAAS,MAAT,EAAiB,YAAW;AAC1B,MAAIC,MAAJ;AACA,MAAIC,KAAJ;AACA,MAAIC,48BAAJ;AAwBAC,YAAU,YAAW;AACnBH,WAAOI,OAAP;AACAH,UAAMI,MAAN;AACD,GAHD;AAKDN,WAAS,eAAT,EAA0B,YAAW;AAClCO,OAAG,uCAAH,EAA4C,YAAW;AACrDL,cAAQM,EAAEL,QAAF,EAAYM,QAAZ,CAAqB,MAArB,CAAR;AACAR,eAAS,IAAIS,WAAWC,IAAf,CAAoBT,MAAMU,IAAN,CAAW,aAAX,CAApB,EAA+C,EAA/C,CAAT;AAEAX,aAAOY,QAAP,CAAgBC,MAAhB,CAAuBC,EAAvB,CAA0BC,EAA1B,CAA6B,QAA7B;AACAf,aAAOgB,OAAP,CAAeH,MAAf,CAAsBC,EAAtB,CAAyBC,EAAzB,CAA4B,QAA5B;AACD,KAND;AAOD,GARF;AAUChB,WAAS,QAAT,EAAmB,YAAW;AAC5BO,OAAG,sBAAH,EAA2B,YAAW;AACpCL,cAAQM,EAAEL,QAAF,EAAYM,QAAZ,CAAqB,MAArB,CAAR;AACAR,eAAS,IAAIS,WAAWC,IAAf,CAAoBT,MAAMU,IAAN,CAAW,aAAX,CAApB,EAA+C,EAA/C,CAAT,CAFoC,CAIpC;;AACAV,YAAMU,IAAN,CAAW,SAAX,EAAsBE,MAAtB,CAA6BI,IAA7B,CAAkCC,IAAlC,CAAuC,MAAvC,EAA+C,UAA/C;AACAjB,YAAMU,IAAN,CAAW,SAAX,EAAsBE,MAAtB,CAA6BI,IAA7B,CAAkCC,IAAlC,CAAuC,iBAAvC,EAA0DjB,MAAMU,IAAN,CAAW,kBAAX,EAA+BO,IAA/B,CAAoC,IAApC,CAA1D;AACAjB,YAAMU,IAAN,CAAW,SAAX,EAAsBE,MAAtB,CAA6BM,GAA7B,CAAiCF,IAAjC,CAAsCC,IAAtC,CAA2C,aAA3C;AACAjB,YAAMU,IAAN,CAAW,SAAX,EAAsBE,MAAtB,CAA6BI,IAA7B,CAAkCC,IAAlC,CAAuC,aAAvC,EAAsD,MAAtD,EARoC,CAUpC;;AACAjB,YAAMU,IAAN,CAAW,kBAAX,EAA+BE,MAA/B,CAAsCI,IAAtC,CAA2CC,IAA3C,CAAgD,MAAhD,EAAwD,KAAxD;AACAjB,YAAMU,IAAN,CAAW,kBAAX,EAA+BE,MAA/B,CAAsCI,IAAtC,CAA2CC,IAA3C,CAAgD,eAAhD,EAAiEjB,MAAMU,IAAN,CAAW,QAAX,EAAqBO,IAArB,CAA0B,IAA1B,CAAjE;AACAjB,YAAMU,IAAN,CAAW,kBAAX,EAA+BE,MAA/B,CAAsCI,IAAtC,CAA2CC,IAA3C,CAAgD,eAAhD,EAAiE,MAAjE;AACAjB,YAAMU,IAAN,CAAW,kBAAX,EAA+BE,MAA/B,CAAsCI,IAAtC,CAA2CC,IAA3C,CAAgD,eAAhD,EAAiE,OAAjE,EAdoC,CAgBpC;;AACAjB,YAAMU,IAAN,CAAW,kBAAX,EAA+BS,MAA/B,GAAwCP,MAAxC,CAA+CI,IAA/C,CAAoDC,IAApD,CAAyD,MAAzD,EAAiE,cAAjE;AACD,KAlBD;AAmBD,GApBD;AAsBAnB,WAAS,aAAT,EAAwB,YAAW;AACjCO,OAAG,2CAAH,EAAgD,YAAW;AACzDL,cAAQM,EAAEL,QAAF,EAAYM,QAAZ,CAAqB,MAArB,CAAR;AACAR,eAAS,IAAIS,WAAWC,IAAf,CAAoBT,MAAMU,IAAN,CAAW,aAAX,CAApB,EAA+C,EAA/C,CAAT;AAEAX,aAAOqB,SAAP,CAAiBpB,MAAMU,IAAN,CAAW,SAAX,CAAjB;AACAV,YAAMU,IAAN,CAAW,SAAX,EAAsBE,MAAtB,CAA6BC,EAA7B,CAAgCQ,OAAhC;AACD,KAND;AAQAhB,OAAG,sCAAH,EAA2C,YAAW;AACpDL,cAAQM,EAAEL,QAAF,EAAYM,QAAZ,CAAqB,MAArB,CAAR;AACAR,eAAS,IAAIS,WAAWC,IAAf,CAAoBT,MAAMU,IAAN,CAAW,aAAX,CAApB,EAA+C,EAA/C,CAAT;AAEAX,aAAOqB,SAAP,CAAiB,SAAjB;AACApB,YAAMU,IAAN,CAAW,SAAX,EAAsBE,MAAtB,CAA6BC,EAA7B,CAAgCQ,OAAhC;AACD,KAND;AAOAhB,OAAG,wDAAH,EAA6D,YAAW;AACtEL,cAAQM,EAAEL,QAAF,EAAYM,QAAZ,CAAqB,MAArB,CAAR;AACAR,eAAS,IAAIS,WAAWC,IAAf,CAAoBT,MAAMU,IAAN,CAAW,aAAX,CAApB,EAA+C,EAA/C,CAAT;AAEAX,aAAOqB,SAAP,CAAiB,UAAjB;AACApB,YAAMU,IAAN,CAAW,SAAX,EAAsBE,MAAtB,CAA6BC,EAA7B,CAAgCQ,OAAhC;AACD,KAND;AAOD,GAvBD;AAyBAvB,WAAS,oBAAT,EAA+B,YAAW;AACxCO,OAAG,wBAAH,EAA6B,YAAW;AACtCL,cAAQM,EAAEL,QAAF,EAAYM,QAAZ,CAAqB,MAArB,CAAR;AACAR,eAAS,IAAIS,WAAWC,IAAf,CAAoBT,MAAMU,IAAN,CAAW,aAAX,CAApB,EAA+C,EAA/C,CAAT;AAEAX,aAAOqB,SAAP,CAAiB,SAAjB;AACApB,YAAMU,IAAN,CAAW,SAAX,EAAsBE,MAAtB,CAA6BC,EAA7B,CAAgCQ,OAAhC;AACArB,YAAMU,IAAN,CAAW,SAAX,EAAsBE,MAAtB,CAA6BI,IAA7B,CAAkCM,KAAlC,CAAwC,WAAxC;AACD,KAPD;AASAjB,OAAG,mCAAH,EAAwC,YAAW;AACjDL,cAAQM,EAAEL,QAAF,EAAYM,QAAZ,CAAqB,MAArB,CAAR;AACAR,eAAS,IAAIS,WAAWC,IAAf,CAAoBT,MAAMU,IAAN,CAAW,aAAX,CAApB,EAA+C,EAA/C,CAAT;AAEAX,aAAOqB,SAAP,CAAiB,SAAjB;AACApB,YAAMU,IAAN,CAAW,SAAX,EAAsBE,MAAtB,CAA6BI,IAA7B,CAAkCE,GAAlC,CAAsCD,IAAtC,CAA2C,aAA3C;AACAjB,YAAMU,IAAN,CAAW,kBAAX,EAA+BE,MAA/B,CAAsCI,IAAtC,CAA2CC,IAA3C,CAAgD,eAAhD,EAAiE,MAAjE;AACD,KAPD;AASAZ,OAAG,oBAAH,EAAyB,YAAW;AAClCL,cAAQM,EAAEL,QAAF,EAAYM,QAAZ,CAAqB,MAArB,CAAR;AACAR,eAAS,IAAIS,WAAWC,IAAf,CAAoBT,MAAMU,IAAN,CAAW,aAAX,CAApB,EAA+C,EAA/C,CAAT;AAEAX,aAAOqB,SAAP,CAAiB,SAAjB;AACApB,YAAMU,IAAN,CAAW,SAAX,EAAsBE,MAAtB,CAA6BC,EAA7B,CAAgCU,MAAhC;AACAvB,YAAMU,IAAN,CAAW,SAAX,EAAsBE,MAAtB,CAA6BM,GAA7B,CAAiCF,IAAjC,CAAsCM,KAAtC,CAA4C,WAA5C;AACD,KAPD;AASAjB,OAAG,qCAAH,EAA0C,YAAW;AACnDL,cAAQM,EAAEL,QAAF,EAAYM,QAAZ,CAAqB,MAArB,CAAR;AACAR,eAAS,IAAIS,WAAWC,IAAf,CAAoBT,MAAMU,IAAN,CAAW,aAAX,CAApB,EAA+C,EAA/C,CAAT;AAEAX,aAAOqB,SAAP,CAAiB,SAAjB;AACApB,YAAMU,IAAN,CAAW,SAAX,EAAsBE,MAAtB,CAA6BC,EAA7B,CAAgCG,IAAhC,CAAqCC,IAArC,CAA0C,aAA1C,EAAyD,MAAzD;AACAjB,YAAMU,IAAN,CAAW,kBAAX,EAA+BE,MAA/B,CAAsCC,EAAtC,CAAyCG,IAAzC,CAA8CC,IAA9C,CAAmD,eAAnD,EAAoE,OAApE;AACD,KAPD;AASAZ,OAAG,gDAAH,EAAqD,UAASmB,IAAT,EAAe;AAClExB,cAAQM,EAAEL,QAAF,EAAYM,QAAZ,CAAqB,MAArB,CAAR;AACAR,eAAS,IAAIS,WAAWC,IAAf,CAAoBT,MAAMU,IAAN,CAAW,aAAX,CAApB,EAA+C,EAA/C,CAAT;AAEAV,YAAMyB,GAAN,CAAU,gBAAV,EAA4B,UAASC,CAAT,EAAYC,OAAZ,EAAqB;AAC/CD,UAAEE,eAAF;AACA5B,cAAMU,IAAN,CAAW,kBAAX,EAA+BS,MAA/B,GAAwC,CAAxC,EAA2CP,MAA3C,CAAkDC,EAAlD,CAAqDgB,KAArD,CAA2DF,QAAQ,CAAR,CAA3D;AACAH;AACD,OAJD;AAMAzB,aAAOqB,SAAP,CAAiB,SAAjB;AACD,KAXD;AAYD,GAjDD;AAmDAtB,WAAS,iBAAT,EAA4B,YAAW;AACrCO,OAAG,qCAAH,EAA0C,YAAW;AACnDL,cAAQM,EAAEL,QAAF,EAAYM,QAAZ,CAAqB,MAArB,CAAR;AACAR,eAAS,IAAIS,WAAWC,IAAf,CAAoBT,MAAMU,IAAN,CAAW,aAAX,CAApB,EAA+C,EAA/C,CAAT;AAEAV,YAAMU,IAAN,CAAW,kBAAX,EAA+BoB,KAA/B,GACGC,OADH,CACWC,OAAOC,iBAAP,CAAyB,aAAzB,CADX;AAGAjC,YAAMU,IAAN,CAAW,SAAX,EAAsBE,MAAtB,CAA6BC,EAA7B,CAAgCQ,OAAhC;AACArB,YAAMU,IAAN,CAAW,SAAX,EAAsBE,MAAtB,CAA6BI,IAA7B,CAAkCM,KAAlC,CAAwC,WAAxC;AACD,KATD;AAUAjB,OAAG,oCAAH,EAAyC,YAAW;AAClDL,cAAQM,EAAEL,QAAF,EAAYM,QAAZ,CAAqB,MAArB,CAAR;AACAR,eAAS,IAAIS,WAAWC,IAAf,CAAoBT,MAAMU,IAAN,CAAW,aAAX,CAApB,EAA+C,EAA/C,CAAT;AAEAV,YAAMU,IAAN,CAAW,kBAAX,EAA+BoB,KAA/B,GACGC,OADH,CACWC,OAAOC,iBAAP,CAAyB,YAAzB,CADX;AAGAjC,YAAMU,IAAN,CAAW,SAAX,EAAsBE,MAAtB,CAA6BC,EAA7B,CAAgCQ,OAAhC;AACArB,YAAMU,IAAN,CAAW,SAAX,EAAsBE,MAAtB,CAA6BI,IAA7B,CAAkCM,KAAlC,CAAwC,WAAxC;AACD,KATD;AAUAjB,OAAG,wCAAH,EAA6C,YAAW;AACtDL,cAAQM,EAAEL,QAAF,EAAYM,QAAZ,CAAqB,MAArB,CAAR;AACAR,eAAS,IAAIS,WAAWC,IAAf,CAAoBT,MAAMU,IAAN,CAAW,aAAX,CAApB,EAA+C,EAA/C,CAAT;AAEAV,YAAMU,IAAN,CAAW,kBAAX,EAA+BoB,KAA/B,GACGC,OADH,CACWC,OAAOC,iBAAP,CAAyB,YAAzB,CADX;AAGAjC,YAAMU,IAAN,CAAW,SAAX,EAAsBE,MAAtB,CAA6BC,EAA7B,CAAgCQ,OAAhC;AACArB,YAAMU,IAAN,CAAW,SAAX,EAAsBE,MAAtB,CAA6BI,IAA7B,CAAkCM,KAAlC,CAAwC,WAAxC;AACD,KATD;AAUAjB,OAAG,sCAAH,EAA2C,YAAW;AACpDL,cAAQM,EAAEL,QAAF,EAAYM,QAAZ,CAAqB,MAArB,CAAR;AACAR,eAAS,IAAIS,WAAWC,IAAf,CAAoBT,MAAMU,IAAN,CAAW,aAAX,CAApB,EAA+C,EAA/C,CAAT;AAEAV,YAAMU,IAAN,CAAW,kBAAX,EAA+BoB,KAA/B,GACGC,OADH,CACWC,OAAOC,iBAAP,CAAyB,UAAzB,CADX;AAGAjC,YAAMU,IAAN,CAAW,SAAX,EAAsBE,MAAtB,CAA6BC,EAA7B,CAAgCQ,OAAhC;AACArB,YAAMU,IAAN,CAAW,SAAX,EAAsBE,MAAtB,CAA6BI,IAA7B,CAAkCM,KAAlC,CAAwC,WAAxC;AACD,KATD;AAUD,GAzCD;AA0CD,CAtLD","file":"packages/zurb:foundation-sites/test/javascript/components/tabs.js.map","sourcesContent":["describe('Tabs', function() {\n  var plugin;\n  var $html;\n  var template = `\n    <div>\n      <ul class=\"tabs\" data-tabs id=\"example-tabs\">\n        <li class=\"tabs-title is-active\"><a href=\"#panel1\" aria-selected=\"true\">Tab 1</a></li>\n        <li class=\"tabs-title\"><a href=\"#panel2\">Tab 2</a></li>\n        <li class=\"tabs-title\"><a data-tabs-target=\"panel3\" href=\"#/panel3\">Tab 3</a></li>\n      </ul>\n\n      <div class=\"tabs-content\" data-tabs-content=\"example-tabs\">\n        <div class=\"tabs-panel is-active\" id=\"panel1\">\n          <p>one</p>\n          <p>Check me out! I'm a super cool Tab panel with text content!</p>\n        </div>\n        <div class=\"tabs-panel\" id=\"panel2\">\n          <p>two</p>\n          <p>Check me out! I'm a super cool Tab panel with text content!</p>\n        </div>\n        <div class=\"tabs-panel\" id=\"panel3\">\n          <p>three</p>\n          <p>Check me out! I'm a super cool Tab panel with text content!</p>\n        </div>\n      </div>\n    </div>`;\n\n  afterEach(function() {\n    plugin.destroy();\n    $html.remove();\n  });\n\n describe('constructor()', function() {\n    it('stores the element and plugin options', function() {\n      $html = $(template).appendTo('body');\n      plugin = new Foundation.Tabs($html.find('[data-tabs]'), {});\n\n      plugin.$element.should.be.an('object');\n      plugin.options.should.be.an('object');\n    });\n  });\n\n  describe('init()', function() {\n    it('sets ARIA attributes', function() {\n      $html = $(template).appendTo('body');\n      plugin = new Foundation.Tabs($html.find('[data-tabs]'), {});\n\n      // Panels\n      $html.find('#panel1').should.have.attr('role', 'tabpanel');\n      $html.find('#panel1').should.have.attr('aria-labelledby', $html.find('[href=\"#panel1\"]').attr('id'));\n      $html.find('#panel1').should.not.have.attr('aria-hidden');\n      $html.find('#panel2').should.have.attr('aria-hidden', 'true');\n\n      // Links\n      $html.find('[href=\"#panel1\"]').should.have.attr('role', 'tab');\n      $html.find('[href=\"#panel1\"]').should.have.attr('aria-controls', $html.find('panel1').attr('id'));\n      $html.find('[href=\"#panel1\"]').should.have.attr('aria-selected', 'true');\n      $html.find('[href=\"#panel2\"]').should.have.attr('aria-selected', 'false');\n\n      // Tab list items\n      $html.find('[href=\"#panel1\"]').parent().should.have.attr('role', 'presentation');\n    });\n  });\n\n  describe('selectTab()', function() {\n    it('opens the selected tab via jQuery element', function() {\n      $html = $(template).appendTo('body');\n      plugin = new Foundation.Tabs($html.find('[data-tabs]'), {});\n\n      plugin.selectTab($html.find('#panel2'));\n      $html.find('#panel2').should.be.visible;\n    });\n\n    it('opens the selected tab via id string', function() {\n      $html = $(template).appendTo('body');\n      plugin = new Foundation.Tabs($html.find('[data-tabs]'), {});\n\n      plugin.selectTab('#panel2');\n      $html.find('#panel2').should.be.visible;\n    });\n    it('opens the selected tab with data-tabs-target attribute', function() {\n      $html = $(template).appendTo('body');\n      plugin = new Foundation.Tabs($html.find('[data-tabs]'), {});\n\n      plugin.selectTab('#/panel3');\n      $html.find('#panel3').should.be.visible;\n    });\n  });\n\n  describe('_handleTabChange()', function() {\n    it('opens the selected tab', function() {\n      $html = $(template).appendTo('body');\n      plugin = new Foundation.Tabs($html.find('[data-tabs]'), {});\n\n      plugin.selectTab('#panel2');\n      $html.find('#panel2').should.be.visible;\n      $html.find('#panel2').should.have.class('is-active');\n    });\n\n    it('sets ARIA attributes for open tab', function() {\n      $html = $(template).appendTo('body');\n      plugin = new Foundation.Tabs($html.find('[data-tabs]'), {});\n\n      plugin.selectTab('#panel2');\n      $html.find('#panel2').should.have.not.attr('aria-hidden');\n      $html.find('[href=\"#panel2\"]').should.have.attr('aria-selected', 'true');\n    });\n\n    it('hides the open tab', function() {\n      $html = $(template).appendTo('body');\n      plugin = new Foundation.Tabs($html.find('[data-tabs]'), {});\n\n      plugin.selectTab('#panel2');\n      $html.find('#panel1').should.be.hidden;\n      $html.find('#panel1').should.not.have.class('is-active');\n    });\n\n    it('sets ARIA attributes for closed tab', function() {\n      $html = $(template).appendTo('body');\n      plugin = new Foundation.Tabs($html.find('[data-tabs]'), {});\n\n      plugin.selectTab('#panel2');\n      $html.find('#panel1').should.be.have.attr('aria-hidden', 'true');\n      $html.find('[href=\"#panel1\"]').should.be.have.attr('aria-selected', 'false');\n    });\n\n    it('fires change.zf.tabs event with target as data', function(done) {\n      $html = $(template).appendTo('body');\n      plugin = new Foundation.Tabs($html.find('[data-tabs]'), {});\n\n      $html.one('change.zf.tabs', function(e, $target) {\n        e.stopPropagation();\n        $html.find('[href=\"#panel2\"]').parent()[0].should.be.equal($target[0]);\n        done();\n      });\n\n      plugin.selectTab('#panel2');\n    });\n  });\n\n  describe('keyboard events', function() {\n    it('switches to next tab on ARROW_RIGHT', function() {\n      $html = $(template).appendTo('body');\n      plugin = new Foundation.Tabs($html.find('[data-tabs]'), {});\n\n      $html.find('[href=\"#panel1\"]').focus()\n        .trigger(window.mockKeyboardEvent('ARROW_RIGHT'));\n\n      $html.find('#panel2').should.be.visible;\n      $html.find('#panel2').should.have.class('is-active');\n    });\n    it('switches to next tab on ARROW_DOWN', function() {\n      $html = $(template).appendTo('body');\n      plugin = new Foundation.Tabs($html.find('[data-tabs]'), {});\n\n      $html.find('[href=\"#panel1\"]').focus()\n        .trigger(window.mockKeyboardEvent('ARROW_DOWN'));\n\n      $html.find('#panel2').should.be.visible;\n      $html.find('#panel2').should.have.class('is-active');\n    });\n    it('switches to previous tab on ARROW_LEFT', function() {\n      $html = $(template).appendTo('body');\n      plugin = new Foundation.Tabs($html.find('[data-tabs]'), {});\n\n      $html.find('[href=\"#panel2\"]').focus()\n        .trigger(window.mockKeyboardEvent('ARROW_LEFT'));\n\n      $html.find('#panel1').should.be.visible;\n      $html.find('#panel1').should.have.class('is-active');\n    });\n    it('switches to previous tab on ARROW_UP', function() {\n      $html = $(template).appendTo('body');\n      plugin = new Foundation.Tabs($html.find('[data-tabs]'), {});\n\n      $html.find('[href=\"#panel2\"]').focus()\n        .trigger(window.mockKeyboardEvent('ARROW_UP'));\n\n      $html.find('#panel1').should.be.visible;\n      $html.find('#panel1').should.have.class('is-active');\n    });\n  });\n});\n"]},"hash":"684fe52333678b63324ae7a528e17fe6ec906295"}
